tuno/__init__.py
tuno/__main__.py
tuno/client/UnoApp.py
tuno/client/UnoClient.py
tuno/client/__init__.py
tuno/client/__main__.py
tuno/client/config.py
tuno/client/components/CardColorLabel.py
tuno/client/components/CardLabel.py
tuno/client/components/CheckboxContainer.py
tuno/client/components/Players.py
tuno/client/components/__init__.py
tuno/client/components/CardsScreen/__init__.py
tuno/client/components/CardsScreen/styles.tcss
tuno/client/components/ConnectScreen/__init__.py
tuno/client/components/ConnectScreen/styles.tcss
tuno/client/components/InGameScreen/Sidebar.py
tuno/client/components/InGameScreen/__init__.py
tuno/client/components/InGameScreen/styles.tcss
tuno/client/components/LoadingScreen/__init__.py
tuno/client/components/LoadingScreen/styles.tcss
tuno/client/components/PendingScreen/__init__.py
tuno/client/components/PendingScreen/styles.tcss
tuno/client/components/RulesScreen/__init__.py
tuno/client/components/RulesScreen/styles.tcss
tuno/client/event_handlers/__init__.py
tuno/client/event_handlers/cards.py
tuno/client/event_handlers/end_of_connection.py
tuno/client/event_handlers/game_state.py
tuno/client/event_handlers/notification.py
tuno/client/event_handlers/subscription_change.py
tuno/client/utils/ApiContext.py
tuno/client/utils/LoadingContext.py
tuno/server/__init__.py
tuno/server/config.py
tuno/server/exceptions.py
tuno/server/models/Game.py
tuno/server/models/Player.py
tuno/server/models/__init__.py
tuno/server/routes/__init__.py
tuno/server/routes/game/rules.py
tuno/server/routes/game/start.py
tuno/server/routes/game/stop.py
tuno/server/routes/player/kick.py
tuno/server/routes/player/play.py
tuno/server/routes/player/sub.py
tuno/server/utils/Logger.py
tuno/server/utils/checkers.py
tuno/server/utils/create_deck.py
tuno/server/utils/format_optional_operator.py
tuno/shared/LazyTimer.py
tuno/shared/ThreadLockContext.py
tuno/shared/__init__.py
tuno/shared/check_play.py
tuno/shared/constraints.py
tuno/shared/deck.py
tuno/shared/loop.py
tuno-0.2.1.dist-info/METADATA
tuno-0.2.1.dist-info/WHEEL
tuno-0.2.1.dist-info/entry_points.txt
tuno-0.2.1.dist-info/licenses/LICENSE
tuno-0.2.1.dist-info/RECORD
