Metadata-Version: 2.4
Name: tuno
Version: 0.2.1
Summary: UNO right in your terminal, with both server and client.
Project-URL: Homepage, https://github.com/huang2002/tuno
Project-URL: Changelog, https://github.com/huang2002/tuno/blob/main/CHANGELOG.md
Project-URL: License, https://github.com/huang2002/tuno/blob/main/LICENSE
Author-email: huang2002 <huanghaihua2002@qq.com>
License-Expression: ISC
License-File: LICENSE
Classifier: License :: OSI Approved :: ISC License (ISCL)
Classifier: Operating System :: OS Independent
Classifier: Programming Language :: Python :: 3
Requires-Python: >=3.12
Requires-Dist: click==8.1.8
Requires-Dist: flask==3.1.0
Requires-Dist: requests-sse==0.5.0
Requires-Dist: requests==2.32.3
Requires-Dist: textual==1.0.0
Provides-Extra: dev
Requires-Dist: black==24.8.0; extra == 'dev'
Requires-Dist: isort==6.0.0; extra == 'dev'
Requires-Dist: mypy==1.15.0; extra == 'dev'
Requires-Dist: textual-dev==1.7.0; extra == 'dev'
Requires-Dist: types-requests==2.32.0.20241016; extra == 'dev'
